litemark/__init__.py
litemark/__main__.py
litemark/core/__init__.py
litemark/core/scanner.py
litemark/core/style.py
litemark/core/util.py
litemark/core/viewer.py
litemark/demo/header.png
litemark/demo/litemark-demo.md
litemark/pyrustic_data/backstage/config/build.json
litemark/pyrustic_data/backstage/config/init.json
litemark/pyrustic_data/backstage/config/release.json
litemark/pyrustic_data/backstage/data/build_report.json
litemark/pyrustic_data/backstage/data/github_release_form.json
litemark/pyrustic_data/backstage/hooking/build.json
litemark/pyrustic_data/backstage/hooking/init.json
litemark/pyrustic_data/backstage/hooking/release.json
litemark/pyrustic_data/backstage/report/build_report.json
litemark/pyrustic_data/backstage/report/release_report.json
litemark/pyrustic_data/hubstore/img.json
litemark/pyrustic_data/hubstore/promotion.json
tests/__init__.py
tests/__main__.py
litemark-0.0.4.dist-info/LICENSE
litemark-0.0.4.dist-info/METADATA
litemark-0.0.4.dist-info/WHEEL
litemark-0.0.4.dist-info/entry_points.txt
litemark-0.0.4.dist-info/top_level.txt
litemark-0.0.4.dist-info/RECORD
