Metadata-Version: 2.1
Name: litemark
Version: 0.0.4
Summary: Lightweight Markdown dialect for Python desktop apps
Home-page: https://github.com/pyrustic/litemark
Author: Pyrustic Evangelist
Author-email: rusticalex@yahoo.com
Maintainer: Pyrustic Evangelist
Maintainer-email: rusticalex@yahoo.com
License: MIT
Keywords: markdown,litemark,lightweight,pyrustic,codegame,desktop,gui,viewer,renderer,markup
Platform: UNKNOWN
Classifier: Programming Language :: Python :: 3
Classifier: License :: OSI Approved :: MIT License
Classifier: Operating System :: OS Independent
Requires-Python: >=3.5
License-File: LICENSE
